{
  "content": [
    {
      "id": "swarm",
      "type": "swarm",
      "name": "Стая",
      "description": "Получает <color=#00FF00>+1</color> урон за каждого союзника по близости.",
      "icon": "swarm_passive_icon",
      "params": {
        "damage": 1,
        "duration": 1
      }
    },
    {
      "id": "lifesteal_50",
      "type": "lifesteal",
      "name": "Вампиризм%",
      "description": "Восстанавливает 50% от нанесённого урона в виде здоровья",
      "icon": "passives/lifesteal_icon",
      "params": {
        "percent": 0.5
      }
    },
    {
      "id": "lifesteal_25",
      "type": "lifesteal",
      "name": "Вампиризм",
      "description": "Восстанавливает 25% от нанесённого урона в виде здоровья",
      "icon": "passives/lifesteal_icon",
      "params": {
        "percent": 0.25
      }
    },
    {
      "id": "execute_30",
      "type": "execute",
      "name": "Казнь",
      "description": "Мгновенно убивает врагов с здоровьем ниже 30%",
      "icon": "passives/execute_icon",
      "params": {
        "threshold": 0.3,
        "multiplier": 2
      }
    },
    {
      "id": "crit_20",
      "type": "critical",
      "name": "Критический удар",
      "description": "20% шанс нанести двойной урон",
      "icon": "passives/crit_icon",
      "params": {
        "chance": 0.2,
        "multiplier": 2
      }
    },
    {
      "id": "crit_50_3x",
      "type": "critical",
      "name": "Критический удар",
      "description": "50% шанс нанести тройной урон",
      "icon": "passives/crit_icon",
      "params": {
        "chance": 0.5,
        "multiplier": 3
      }
    },
    {
      "id": "thorns_25",
      "type": "thorns",
      "name": "Шипы",
      "description": "Возвращает 25% урона атакующему",
      "icon": "passives/thorns_icon",
      "params": {
        "percent": 0.25
      }
    },
    {
      "id": "retreat_slippery",
      "type": "retreat_on_no_kill",
      "name": "Отступление",
      "description": "Отступает на 1 клетку после нанесение не смертельного урона",
      "icon": "escape_passive_icon",
      "params": {
        "distance": 1
      }
    },
    {
      "id": "fortify_tank",
      "type": "fortify",
      "name": "Укрепление",
      "description": "Снижает входящий урон на 1",
      "icon": "passives/fortify_icon",
      "params": {
        "reduction": 1
      }
    },
    {
      "id": "push_on_hit",
      "type": "push_on_hit",
      "name": "Толчок",
      "description": "Толкает врага по направлении атаки. При столкновении наносит <color=#00FF00>+1</color> урон",
      "icon": "impact_passive_icon",
      "params": {
        "bonus_damage": 1
      }
    },
    {
      "id": "momentum",
      "type": "momentum",
      "name": "Инерция",
      "description": "Каждая атака прибавляет <color=#00FF00>+0.5</color> урона. Сбрасывается при получении урона.",
      "icon": "momentum_passive_icon",
      "params": {
        "bonus_damage": 0.5
      }
    },
    {
      "id": "agile_dodge",
      "type": "agile_dodge",
      "name": "Уклонение",
      "description": "Дает <color=#00FF00>50%</color> уклонения на 1 ход, после передвижения",
      "icon": "agile_dodge_passive",
      "params": {
        "chance": 0.5
      }
    },
    {
      "id": "first_shot",
      "type": "first_shot",
      "name": "Первый выстрел",
      "description": "Первый выстрел по врагу наносит <color=#00FF00>+2</color> урона",
      "icon": "first_shot_passive_icon",
      "params": {
        "bonus_damage": 2
      }
    },
    {
      "id": "fury",
      "type": "fury",
      "name": "Ярость",
      "description": "Каждая атака прибавляет <color=#00FF00>+0.5</color> урона. Сбрасывается при получении урона. Макс.4",
      "icon": "momentum_passive_icon",
      "params": {
        "damage": 0.5,
        "max_stacks": 4
      }
    },
    {
      "id": "inspiration",
      "type": "inspiration",
      "name": "Вдохновение",
      "description": "Даёт союзникам рядом +2 к атаке и защите на 2 хода",
      "icon": "passives/inspiration_icon",
      "params": {
        "attack_bonus": 2,
        "defence_bonus": 2,
        "evasion_bonus": 0.15,
        "duration": 2
      }
    },
    {
      "id": "provocation",
      "type": "provocation",
      "name": "Провокация",
      "description": "Враги по близости фигуры обязаны атаковать ее",
      "icon": "provocation_passive_icon",
      "params": {}
    },
    {
      "id": "desperation",
      "type": "desperation",
      "name": "Отчаяние",
      "description": "Когда остается в одиночестве, урон сокращается до <color=#FF0000>1</color>. Позволяет атаковать ближайшие клетки",
      "icon": "desperation_passive_icon",
      "params": {}
    },
    {
      "id": "royal_presence",
      "type": "royal_presence",
      "name": "Королевское присутствие",
      "description": "+100% урона союзникам в радиусе 2 клеток",
      "icon": "royal_presence_passive_icon",
      "params": {
        "damage_bonus": 1,
        "aura_radius": 2
      }
    },
    {
      "id": "escape",
      "type": "escape",
      "name": "Побег",
      "description": "Может уйти с поля боя при низком здоровье",
      "icon": "escape_passive_icon",
      "params": {}
    },
    {
      "id": "impact",
      "type": "impact",
      "name": "Удар",
      "description": "+2 урона к первой атаке",
      "icon": "impact_passive_icon",
      "params": {
        "bonus_damage": 2
      }
    },
    {
      "id": "melee_override",
      "type": "melee_override",
      "name": "Ближний бой",
      "description": "Уменьшает урон в ближнем бою на 50%",
      "icon": "melee_override_passive_icon",
      "params": {
        "melee_damage_multiplier": 0.5
      }
    },
    {
      "id": "splash",
      "type": "splash",
      "name": "Всплеск",
      "description": "Урон по области вокруг цели",
      "icon": "splash_passive_icon",
      "params": {}
    },
    {
      "id": "pierce",
      "type": "pierce",
      "name": "Пронзающий удар",
      "description": "Атака проходит сквозь цель",
      "icon": "pierce_passive_icon",
      "params": {}
    }
  ]
}